mpip/__init__.py
mpip/cli.py
mpipcli-0.4.dist-info/LICENSE
mpipcli-0.4.dist-info/METADATA
mpipcli-0.4.dist-info/WHEEL
mpipcli-0.4.dist-info/entry_points.txt
mpipcli-0.4.dist-info/top_level.txt
mpipcli-0.4.dist-info/RECORD
