Metadata-Version: 2.1
Name: mpipcli
Version: 0.4
Summary: UNKNOWN
Home-page: UNKNOWN
License: UNKNOWN
Platform: UNKNOWN
License-File: LICENSE
Requires-Dist: requests
